soca/__init__.py
soca/__main__.py
soca/assets/about.html
soca/assets/app.js
soca/assets/soca-card.css
soca/assets/styles.css
soca/assets/template.html
soca/assets/img/back_arrow.svg
soca/assets/img/fi_logo.png
soca/assets/img/filter.svg
soca/assets/img/github-default.svg
soca/assets/img/help.png
soca/assets/img/oeg_logo.gif
soca/assets/img/soca-logo.ico
soca/assets/img/soca-logo.png
soca/assets/img/sort.svg
soca/assets/img/statIcon.svg
soca/assets/img/upm_logo.png
soca/assets/language_icons/arduino.svg
soca/assets/language_icons/c++.svg
soca/assets/language_icons/c-sharp.svg
soca/assets/language_icons/c.svg
soca/assets/language_icons/clojure.svg
soca/assets/language_icons/coffeescript.svg
soca/assets/language_icons/css.svg
soca/assets/language_icons/go.svg
soca/assets/language_icons/groovy.svg
soca/assets/language_icons/haskell.svg
soca/assets/language_icons/html.svg
soca/assets/language_icons/java.svg
soca/assets/language_icons/javascript.svg
soca/assets/language_icons/lua.svg
soca/assets/language_icons/matlab.svg
soca/assets/language_icons/objectivec.svg
soca/assets/language_icons/perl.svg
soca/assets/language_icons/php.svg
soca/assets/language_icons/python.svg
soca/assets/language_icons/r.svg
soca/assets/language_icons/ruby.svg
soca/assets/language_icons/scala.svg
soca/assets/language_icons/shell.svg
soca/assets/language_icons/swift.svg
soca/assets/repo_icons/acknowledgement.png
soca/assets/repo_icons/citation.png
soca/assets/repo_icons/copy.svg
soca/assets/repo_icons/docker.png
soca/assets/repo_icons/documentation.png
soca/assets/repo_icons/doi.png
soca/assets/repo_icons/download.png
soca/assets/repo_icons/help.png
soca/assets/repo_icons/installation.png
soca/assets/repo_icons/license.png
soca/assets/repo_icons/notebook.png
soca/assets/repo_icons/ontology.png
soca/assets/repo_icons/owner.svg
soca/assets/repo_icons/paper.png
soca/assets/repo_icons/readme.png
soca/assets/repo_icons/releases.png
soca/assets/repo_icons/requirements.png
soca-0.0.3.dist-info/LICENSE
soca-0.0.3.dist-info/METADATA
soca-0.0.3.dist-info/WHEEL
soca-0.0.3.dist-info/entry_points.txt
soca-0.0.3.dist-info/top_level.txt
soca-0.0.3.dist-info/RECORD
