Metadata-Version: 2.1
Name: soca
Version: 0.0.3
Summary: A python package that given an organization/user name, it will create a software catalog for browsing all repositories or just a single repository in a minimalist card.
Home-page: https://github.com/oeg-upm/soca
Author: Daniel Rodríguez Mariblanca, Miguel Arroyo Márquez, Esteban Gonzalez, Daniel Garijo
Author-email: daniel.garijo@upm.es
Classifier: Programming Language :: Python :: 3
Classifier: Operating System :: OS Independent
Requires-Python: >=3.10.0
License-File: LICENSE
Requires-Dist: somef >=0.9.0
Requires-Dist: requests
Requires-Dist: bs4
Requires-Dist: htmlmin
Requires-Dist: progressbar2
Requires-Dist: mistune
Requires-Dist: Pygments
Requires-Dist: html2image
Requires-Dist: inspect4py
Requires-Dist: click
Requires-Dist: influxdb-client
Requires-Dist: configparser
Requires-Dist: DateTime
Requires-Dist: pathlib
Requires-Dist: nltk
Requires-Dist: validators
